ldap_exporter/__init__.py
ldap_exporter/ldap.py
ldap_exporter/main.py
ldap_exporter/prometheus.py
ldap_exporter/py.typed
ldap_exporter-0.1.0.dist-info/licenses/LICENSE
ldap_exporter-0.1.0.dist-info/WHEEL
ldap_exporter-0.1.0.dist-info/METADATA
ldap_exporter-0.1.0.dist-info/RECORD
