Metadata-Version: 2.4
Name: ldap-exporter
Version: 0.1.0
Summary: A Prometheus exporter proxy for LDAP
Author: Tobias Linkermann
Author-email: Tobias Linkermann <tobias.linkermann@outlook.de>
License-Expression: Apache-2.0
License-File: LICENSE
Classifier: Programming Language :: Python :: 3
Classifier: Operating System :: OS Independent
Requires-Dist: ldap3>=2.9.1
Requires-Dist: prometheus-client>=0.23.1
Requires-Dist: pyyaml>=6.0.3
Requires-Python: >=3.14
Project-URL: Homepage, https://github.com/tschroeder13/ldap-exporter
Project-URL: Issues, https://github.com/tschroeder13/ldap-exporter/issues
